README.md
setup.py
app/__init__.py
app/check.py
app/config.py
app/generate.py
app/main.py
app/pdf.py
binary_quiz.egg-info/PKG-INFO
binary_quiz.egg-info/SOURCES.txt
binary_quiz.egg-info/dependency_links.txt
binary_quiz.egg-info/entry_points.txt
binary_quiz.egg-info/top_level.txt