Metadata-Version: 2.1
Name: binary-quiz
Version: 0.1.6
Summary: A command line application and Python library for generating binary numbers for a human to decode, as well as generating the integers they represent, to check the human's work. Also optionally outputs to PDF.
Home-page: UNKNOWN
Author: Zev Averbach
Author-email: zev@averba.ch
License: MIT
Platform: UNKNOWN
Classifier: Programming Language :: Python :: 3
Classifier: License :: OSI Approved :: MIT License
Classifier: Operating System :: OS Independent
Requires-Python: >=3.5
